kansuji2digit/__init__.py
kansuji2digit/__main__.py
kansuji2digit/_kansuji2digit.pyd
kansuji2digit/kansuji2digit.py
kansuji2digit-0.1.2.dist-info/LICENCE
kansuji2digit-0.1.2.dist-info/METADATA
kansuji2digit-0.1.2.dist-info/WHEEL
kansuji2digit-0.1.2.dist-info/top_level.txt
kansuji2digit-0.1.2.dist-info/RECORD
