Metadata-Version: 2.1
Name: kansuji2digit
Version: 0.1.2
Summary: It convert kansuji to digit.
Home-page: https://github.com/nanamedou/kansuji2digit
Author: nanamedou
License: UNKNOWN
Platform: UNKNOWN
Classifier: Programming Language :: Python :: 3
Classifier: License :: OSI Approved :: MIT License
Classifier: Operating System :: Microsoft :: Windows
Requires-Python: >=3.6
License-File: LICENCE
